beam/VERSION
beam/__init__.py
beam/__main__.py
beam/config.py
beam/host.py
beam/resource.py
beam/vendor.py
beam/tests/__init__.py
beam/tests/test_config.py
beam/tests/test_host.py
beam/tests/test_init.py
beam/tests/test_main.py
beam/tests/test_resource.py
beam/tests/test_vendor.py
beam-0.6.0.dist-info/LICENSE
beam-0.6.0.dist-info/METADATA
beam-0.6.0.dist-info/WHEEL
beam-0.6.0.dist-info/entry_points.txt
beam-0.6.0.dist-info/top_level.txt
beam-0.6.0.dist-info/RECORD
