Metadata-Version: 2.1
Name: beam
Version: 0.6.0
Summary: A lightweight wrapper for the SolusVM client API.
Home-page: https://github.com/gebn/beam
Author: George Brighton
Author-email: oss@gebn.co.uk
License: MIT
Classifier: Development Status :: 5 - Production/Stable
Classifier: Environment :: Console
Classifier: Intended Audience :: Developers
Classifier: License :: OSI Approved :: MIT License
Classifier: Operating System :: OS Independent
Classifier: Programming Language :: Python
Classifier: Programming Language :: Python :: 3.10
Classifier: Programming Language :: Python :: 3.11
Classifier: Topic :: Internet :: WWW/HTTP
Classifier: Topic :: Software Development :: Libraries :: Python Modules
License-File: LICENSE
Requires-Dist: six (>=1.9.0)
Requires-Dist: requests
